<Properties StartupConfiguration="{F42E8364-5FAD-4BB8-B4BD-9353ADAFE87C}|Default">
  <MonoDevelop.Ide.Workbench ActiveDocument="BlazorChatSampleHub.cs">
    <Files>
      <File FileName="BlazorChatSampleHub.cs" Line="1" Column="1" />
    </Files>
    <Pads>
      <Pad Id="ProjectPad">
        <State name="__root__">
          <Node name="BlazorChat" expanded="True">
            <Node name="BlazorChat" expanded="True">
              <Node name="BlazorChatSampleHub.cs" selected="True" />
            </Node>
          </Node>
        </State>
      </Pad>
    </Pads>
  </MonoDevelop.Ide.Workbench>
  <MonoDevelop.Ide.ItemProperties.BlazorChat PreferredExecutionTarget="/Applications/Google Chrome.app" />
  <MonoDevelop.Ide.DebuggingService.PinnedWatches />
  <MonoDevelop.Ide.Workspace ActiveConfiguration="Debug" />
  <MonoDevelop.Ide.DebuggingService.Breakpoints>
    <BreakpointStore />
  </MonoDevelop.Ide.DebuggingService.Breakpoints>
  <MultiItemStartupConfigurations />
</Properties>